py_plugin_feeds/__init__.py
py_plugin_feeds/py_plugin_feeds.py
py_plugin_feeds/abi/token/token.json
py_plugin_feeds/mapping/__init__.py
py_plugin_feeds/mapping/list.json
py_plugin_feeds/mapping/token_mapping.py
py_plugin_feeds-1.0.11.dist-info/METADATA
py_plugin_feeds-1.0.11.dist-info/WHEEL
py_plugin_feeds-1.0.11.dist-info/top_level.txt
py_plugin_feeds-1.0.11.dist-info/RECORD
